clyrdia_cli.py
clyrdia/__init__.py
clyrdia/__main__.py
clyrdia/cli.py
clyrdia/cli_mvp.py
clyrdia/config.py
clyrdia/dashboard.py
clyrdia/core/__init__.py
clyrdia/core/benchmarking.py
clyrdia/core/caching.py
clyrdia/core/console.py
clyrdia/core/database.py
clyrdia/core/decorators.py
clyrdia/core/env_loader.py
clyrdia/core/evaluator.py
clyrdia/core/licensing.py
clyrdia/core/models.py
clyrdia/core/providers.py
clyrdia/utils/__init__.py
clyrdia_cli-2.0.1.dist-info/licenses/LICENSE
clyrdia_cli-2.0.1.dist-info/METADATA
clyrdia_cli-2.0.1.dist-info/WHEEL
clyrdia_cli-2.0.1.dist-info/entry_points.txt
clyrdia_cli-2.0.1.dist-info/top_level.txt
clyrdia_cli-2.0.1.dist-info/RECORD
