Metadata-Version: 2.4
Name: clyrdia-cli
Version: 2.0.1
Summary: State-of-the-Art AI Benchmarking for CI/CD
Home-page: https://clyrdia.com
Author: Clyrdia Team
Author-email: Clyrdia Team <team@clyrdia.com>
Maintainer-email: Clyrdia Team <team@clyrdia.com>
License: MIT
Project-URL: Homepage, https://clyrdia.com
Keywords: ai,benchmarking,machine learning,testing,evaluation,openai,anthropic
Classifier: Development Status :: 5 - Production/Stable
Classifier: Intended Audience :: Developers
Classifier: Intended Audience :: Science/Research
Classifier: Operating System :: OS Independent
Classifier: Programming Language :: Python :: 3
Classifier: Programming Language :: Python :: 3.8
Classifier: Programming Language :: Python :: 3.9
Classifier: Programming Language :: Python :: 3.10
Classifier: Programming Language :: Python :: 3.11
Classifier: Programming Language :: Python :: 3.12
Classifier: Topic :: Scientific/Engineering :: Artificial Intelligence
Classifier: Topic :: Software Development :: Testing
Classifier: Topic :: Software Development :: Libraries :: Python Modules
Requires-Python: >=3.8
License-File: LICENSE
Requires-Dist: typer>=0.9.0
Requires-Dist: rich>=13.0.0
Requires-Dist: numpy>=1.21.0
Requires-Dist: pandas>=1.3.0
Requires-Dist: aiohttp>=3.8.0
Requires-Dist: requests>=2.28.0
Requires-Dist: pyyaml>=6.0
Requires-Dist: openai>=1.0.0
Requires-Dist: anthropic>=0.7.0
Requires-Dist: psutil>=5.8.0
Requires-Dist: python-dotenv>=1.0.0
Requires-Dist: httpx>=0.24.0
Requires-Dist: plotly>=5.0.0
Dynamic: author
Dynamic: home-page
Dynamic: license-file
Dynamic: requires-python
